funinstall/__init__.py
funinstall/command.py
funinstall/common/__init__.py
funinstall/install/__init__.py
funinstall/install/brew.py
funinstall/install/code_server.py
funinstall/install/command.py
funinstall/install/frpc.py
funinstall/install/go.py
funinstall/install/newapi.py
funinstall/install/nodejs.py
funinstall/install/oneapi.py
funinstall/install/onehub.py
funinstall/install/ossutil.py
funinstall/install/uif.py
funinstall/install/v2rayA.py
funinstall/install/funjupyter/__init__.py
funinstall/install/funjupyter/config.py
funinstall/install/funjupyter/run.py
funinstall-1.0.59.dist-info/METADATA
funinstall-1.0.59.dist-info/WHEEL
funinstall-1.0.59.dist-info/entry_points.txt
funinstall-1.0.59.dist-info/top_level.txt
funinstall-1.0.59.dist-info/RECORD
