Metadata-Version: 2.4
Name: funinstall
Version: 1.0.59
Summary: funinstall 快速安装一些开发工具
Author-email: 牛哥 <niuliangtao@qq.com>, farfarfun <farfarfun@qq.com>
Maintainer-email: 牛哥 <niuliangtao@qq.com>, farfarfun <farfarfun@qq.com>
Project-URL: Organization, https://github.com/farfarfun
Project-URL: Repository, https://github.com/farfarfun/funinstall
Project-URL: Releases, https://github.com/farfarfun/funinstall/releases
Requires-Python: >=3.8
Requires-Dist: funbuild>=1.6.3
Requires-Dist: funsecret>=1.4.56
Requires-Dist: funserver>=1.0.46
Requires-Dist: funutil>=1.0.50
